byted_overpass_tiktok_recommend_sort_cpp/__init__.py
byted_overpass_tiktok_recommend_sort_cpp-0.0.1.dist-info/METADATA
byted_overpass_tiktok_recommend_sort_cpp-0.0.1.dist-info/WHEEL
byted_overpass_tiktok_recommend_sort_cpp-0.0.1.dist-info/top_level.txt
byted_overpass_tiktok_recommend_sort_cpp-0.0.1.dist-info/RECORD
